b3j0f/__init__.py
b3j0f/task/condition.py
b3j0f/task/core.py
b3j0f/task/version.py
b3j0f/task/registry.py
b3j0f/task/__init__.py
b3j0f/task/test/condition.py
b3j0f/task/test/core.py
b3j0f/task/test/registry.py
b3j0f/task/test/__init__.py
b3j0f.task-0.0.4.dist-info/DESCRIPTION.rst
b3j0f.task-0.0.4.dist-info/RECORD
b3j0f.task-0.0.4.dist-info/metadata.json
b3j0f.task-0.0.4.dist-info/top_level.txt
b3j0f.task-0.0.4.dist-info/METADATA
b3j0f.task-0.0.4.dist-info/WHEEL
